pca_pwa/__init__.py
pca_pwa/app.py
pca_pwa/static/styles.css
pca_pwa/static/stylish.css
pca_pwa/templates/index.html
pca_pwa/templates/result.html
pca_pwa-1.0.5.dist-info/METADATA
pca_pwa-1.0.5.dist-info/WHEEL
pca_pwa-1.0.5.dist-info/RECORD
