Metadata-Version: 2.1
Name: pca-pwa
Version: 1.0.5
Summary: simplified manner for insights and decision-making, by visualizing complex relationships with PCA web application
Home-page: https://github.com/danymukesha/pca-pwa
License: MIT
Keywords: pca,danymukesha
Author: Dany Mukesha
Author-email: danymukesha@gmail.com
Requires-Python: >=3.11,<4.0
Classifier: License :: OSI Approved :: MIT License
Classifier: Programming Language :: Python :: 3
Classifier: Programming Language :: Python :: 3.11
Classifier: Programming Language :: Python :: 3.12
Requires-Dist: adjusttext (>=1.0,<2.0)
Requires-Dist: flask (>=3.0.0,<4.0.0)
Requires-Dist: matplotlib (>=3.8.2,<4.0.0)
Requires-Dist: openpyxl (>=3.1.2,<4.0.0)
Requires-Dist: pandas (>=2.1.4,<3.0.0)
Requires-Dist: scikit-learn (>=1.3.2,<2.0.0)
Requires-Dist: seaborn (>=0.13.1,<0.14.0)
